{"version": 0.6, "generator": "Overpass API 0.7.62.8 e802775f", "osm3s": {"timestamp_osm_base": "2025-11-23T09:47:30Z", "copyright": "The data included in this document is from www.openstreetmap.org. The data is made available under ODbL."}, "elements": [{"type": "node", "id": 8306619079, "lat": 41.1982575, "lon": 47.1282095, "tags": {"amenity": "cafe", "name": "Kafe"}}, {"type": "way", "id": 893742650, "nodes": [8306631518, 8306631517, 8306619116, 8306619115, 8306631518], "tags": {"leisure": "park"}}, {"type": "node", "id": 8306619115, "lat": 41.19521, "lon": 47.1317755}, {"type": "node", "id": 8306619116, "lat": 41.1950263, "lon": 47.1319216}, {"type": "node", "id": 8306631517, "lat": 41.1949244, "lon": 47.1316776}, {"type": "node", "id": 8306631518, "lat": 41.1951051, "lon": 47.1315408}]}