{"version": 0.6, "generator": "Overpass API 0.7.62.8 e802775f", "osm3s": {"timestamp_osm_base": "2025-11-21T17:59:07Z", "copyright": "The data included in this document is from www.openstreetmap.org. The data is made available under ODbL."}, "elements": [{"type": "way", "id": 1331281992, "nodes": [12317805127, 12317805128, 12317805129, 12317805130, 12317805131, 12317805132, 12317805127], "tags": {"leisure": "park"}}, {"type": "node", "id": 12317805127, "lat": 28.4751063, "lon": 76.9685541}, {"type": "node", "id": 12317805128, "lat": 28.4749767, "lon": 76.9687972}, {"type": "node", "id": 12317805129, "lat": 28.4760208, "lon": 76.9695577}, {"type": "node", "id": 12317805130, "lat": 28.4760053, "lon": 76.9698436}, {"type": "node", "id": 12317805131, "lat": 28.4760869, "lon": 76.9698981}, {"type": "node", "id": 12317805132, "lat": 28.4763291, "lon": 76.9694766}]}